README
setup.py
src/coat/__init__.py
src/coat/php.py
src/coat/utils.py
src/coat/wordpress.py
src/coat/django/__init__.py
src/coat/django/commands.py
src/coat/django/settings.py
src/coat/django/signals.py
src/coat/django/utils.py
src/coat/settings/__init__.py
src/coat/signals/__init__.py
src/fabric_coat.egg-info/PKG-INFO
src/fabric_coat.egg-info/SOURCES.txt
src/fabric_coat.egg-info/dependency_links.txt
src/fabric_coat.egg-info/requires.txt
src/fabric_coat.egg-info/top_level.txt