Metadata-Version: 1.0
Name: fabric-coat
Version: 0.4.5
Summary: Deployment helpers for fabric
Home-page: https://bitbucket.org/madssj/fabric-coat
Author: Rasmus Schlünsen, Mads Sülau Jørgensen
Author-email: rs@konstellation.dk, msj@konstellation.dk
License: BSD
Keywords: fabric coat deployment rsync helper
Platform: UNKNOWN
